datetime_demo_mcp/__init__.py
datetime_demo_mcp/server.py
datetime_demo_mcp-0.1.0.dist-info/METADATA
datetime_demo_mcp-0.1.0.dist-info/WHEEL
datetime_demo_mcp-0.1.0.dist-info/entry_points.txt
datetime_demo_mcp-0.1.0.dist-info/top_level.txt
datetime_demo_mcp-0.1.0.dist-info/RECORD
